mailcow/__init__.py
mailcow/__main__.py
mailcow/cli.py
mailcow/config.py
mailcow/globals.py
mailcow/menu.py
mailcow/utils.py
python_mailcow-1.0.4.dist-info/LICENSE
python_mailcow-1.0.4.dist-info/METADATA
python_mailcow-1.0.4.dist-info/WHEEL
python_mailcow-1.0.4.dist-info/entry_points.txt
python_mailcow-1.0.4.dist-info/top_level.txt
python_mailcow-1.0.4.dist-info/RECORD
