Metadata-Version: 2.1
Name: python-mailcow
Version: 1.0.4
Summary: Interact with mailcow API
Home-page: https://github.com/derJD/python-mailcow
Author: Jean-Denis Gebhardt
Author-email: projects@der-jd.de
License: GPLv3+
Platform: UNKNOWN
Classifier: Environment :: Console
Classifier: Intended Audience :: System Administrators
Classifier: Operating System :: OS Independent
Classifier: Programming Language :: Python :: 3 :: Only
Classifier: Programming Language :: Python :: 3.6
Classifier: Programming Language :: Python :: 3.7
Classifier: Programming Language :: Python :: 3.8
Classifier: Programming Language :: Python :: 3.9
Classifier: License :: OSI Approved :: GNU General Public License v3 or later (GPLv3+)
Classifier: Topic :: System :: Systems Administration
Classifier: Topic :: Utilities
Requires-Python: >=3.6
Requires-Dist: requests
Requires-Dist: pyyaml
Requires-Dist: ptable
Requires-Dist: configparser
